LICENSE
README.md
setup.py
django_morest.egg-info/PKG-INFO
django_morest.egg-info/SOURCES.txt
django_morest.egg-info/dependency_links.txt
django_morest.egg-info/requires.txt
django_morest.egg-info/top_level.txt
morest/__init__.py
morest/admin.py
morest/apps.py
morest/models.py
morest/tests.py
morest/api/__init__.py
morest/api/base.py
morest/core/__init__.py
morest/core/docs.py
morest/core/json.py
morest/core/qs.py
morest/core/search.py
morest/db/__init__.py
morest/db/fields.py
morest/errors/__init__.py
morest/errors/base.py
morest/errors/errors.py
morest/generics/__init__.py
morest/generics/get_object.py
morest/middlewares/__init__.py
morest/middlewares/exceptions.py
morest/middlewares/requestid.py
morest/migrations/__init__.py
morest/serializers/__init__.py
morest/serializers/auth.py
morest/serializers/user.py
morest/templates/admin_form.html
morest/utils/__init__.py
morest/utils/aes.py
morest/utils/order.py
morest/utils/paginator.py
morest/utils/search.py
morest/views/__init__.py
morest/views/admin.py
morest/views/list_view.py
morest/views/auth/__init__.py
morest/views/auth/session.py