Metadata-Version: 2.4
Name: django-morest
Version: 0.1.2
Summary: Django api manager and unifier
Author: Sidq
Author-email: abba.dmytro@gmail.com
License:                                  Apache License
Project-URL: GitHub, https://github.com/sidqdev/django-morest
Project-URL: Telegram, https://t.me/sidqdev
Classifier: Programming Language :: Python :: 3
Classifier: Operating System :: OS Independent
Requires-Python: >=3.9
License-File: LICENSE
Requires-Dist: django
Requires-Dist: djangorestframework
Dynamic: author
Dynamic: author-email
Dynamic: classifier
Dynamic: description
Dynamic: description-content-type
Dynamic: license
Dynamic: license-file
Dynamic: project-url
Dynamic: requires-dist
Dynamic: requires-python
Dynamic: summary
